{"11": {"monday": [[{"subject_id": 11, "subject_name_id": 11, "class_id": 11, "number_of_groups": 2, "subject_length": 1, "lesson_hour_id": 0, "teachers_id": [26], "classroom_id": 21, "is_empty": false, "max_stack": 2, "movable": true, "group": 1, "classroom_types": [1, 2, 3]}, {"subject_id": 2, "subject_name_id": 2, "class_id": 11, "number_of_groups": 2, "subject_length": 1, "lesson_hour_id": 0, "teachers_id": [8], "classroom_id": 5, "is_empty": false, "max_stack": 3, "movable": true, "group": 2, "classroom_types": [1, 2, 3]}], [{"subject_id": 11, "subject_name_id": 11, "class_id": 11, "number_of_groups": 2, "subject_length": 1, "lesson_hour_id": 1, "teachers_id": [26], "classroom_id": 21, "is_empty": false, "max_stack": 2, "movable": true, "group": 1, "classroom_types": [1, 2, 3]}, {"subject_id": 11, "subject_name_id": 11, "class_id": 11, "number_of_groups": 2, "subject_length": 1, "lesson_hour_id": 1, "teachers_id": [23, 26], "classroom_id": 18, "is_empty": false, "max_stack": 2, "movable": true, "group": 2, "classroom_types": [1, 2, 3]}], [{"subject_id": 11, "subject_name_id": 11, "class_id": 11, "number_of_groups": 2, "subject_length": 1, "lesson_hour_id": 2, "teachers_id": [26], "classroom_id": 21, "is_empty": false, "max_stack": 2, "movable": true, "group": 1, "classroom_types": [1, 2, 3]}, {"subject_id": 11, "subject_name_id": 11, "class_id": 11, "number_of_groups": 2, "subject_length": 1, "lesson_hour_id": 2, "teachers_id": [23, 26], "classroom_id": 18, "is_empty": false, "max_stack": 2, "movable": true, "group": 2, "classroom_types": [1, 2, 3]}], [{"subject_id": 6, "subject_name_id": 6, "class_id": 11, "number_of_groups": 1, "subject_length": 1, "lesson_hour_id": 3, "teachers_id": [32], "classroom_id": 1, "is_empty": false, "max_stack": 4, "movable": true, "group": 0, "classroom_types": [1, 2, 3]}], [{"subject_id": 10, "subject_name_id": 10, "class_id": 11, "number_of_groups": 1, "subject_length": 1, "lesson_hour_id": 4, "teachers_id": [36], "classroom_id": 38, "is_empty": false, "max_stack": 3, "movable": true, "group": 0, "classroom_types": [1, 2, 3]}], [{"subject_id": 8, "subject_name_id": 8, "class_id": 11, "number_of_groups": 1, "subject_length": 1, "lesson_hour_id": 5, "teachers_id": [51], "classroom_id": 35, "is_empty": false, "max_stack": 2, "movable": true, "group": 0, "classroom_types": [1, 2, 3]}], [{"subject_id": 5, "subject_name_id": 5, "class_id": 11, "number_of_groups": 1, "subject_length": 1, "lesson_hour_id": 6, "teachers_id": [45], "classroom_id": 29, "is_empty": false, "max_stack": 3, "movable": true, "group": 0, "classroom_types": [1, 2, 3]}], [{"subject_id": 9, "subject_name_id": 9, "class_id": 11, "number_of_groups": 1, "subject_length": 1, "lesson_hour_id": 7, "teachers_id": [46], "classroom_id": 30, "is_empty": false, "max_stack": 2, "movable": true, "group": 0, "classroom_types": [1, 2, 3]}], [{"subject_id": 12, "subject_name_id": 12, "class_id": 11, "number_of_groups": 2, "subject_length": 1, "lesson_hour_id": 8, "teachers_id": [19], "classroom_id": 15, "is_empty": false, "max_stack": 2, "movable": true, "group": 1, "classroom_types": [1, 2, 3]}, {"subject_id": 2, "subject_name_id": 2, "class_id": 11, "number_of_groups": 2, "subject_length": 1, "lesson_hour_id": 8, "teachers_id": [8], "classroom_id": 5, "is_empty": false, "max_stack": 3, "movable": true, "group": 2, "classroom_types": [1, 2, 3]}]], "tuesday": [[{"subject_id": 11, "subject_name_id": 11, "class_id": 11, "number_of_groups": 2, "subject_length": 1, "lesson_hour_id": 0, "teachers_id": [26], "classroom_id": 21, "is_empty": false, "max_stack": 2, "movable": true, "group": 1, "classroom_types": [1, 2, 3]}, {"subject_id": 11, "subject_name_id": 11, "class_id": 11, "number_of_groups": 2, "subject_length": 1, "lesson_hour_id": 0, "teachers_id": [23, 26], "classroom_id": 18, "is_empty": false, "max_stack": 2, "movable": true, "group": 2, "classroom_types": [1, 2, 3]}], [{"subject_id": 1, "subject_name_id": 1, "class_id": 11, "number_of_groups": 2, "subject_length": 1, "lesson_hour_id": 1, "teachers_id": [9], "classroom_id": 6, "is_empty": false, "max_stack": 3, "movable": true, "group": 1, "classroom_types": [1, 2, 3]}, {"subject_id": 1, "subject_name_id": 1, "class_id": 11, "number_of_groups": 2, "subject_length": 1, "lesson_hour_id": 1, "teachers_id": [5, 9], "classroom_id": 2, "is_empty": false, "max_stack": 3, "movable": true, "group": 2, "classroom_types": [1, 2, 3]}], [{"subject_id": 1, "subject_name_id": 1, "class_id": 11, "number_of_groups": 2, "subject_length": 1, "lesson_hour_id": 2, "teachers_id": [9], "classroom_id": 6, "is_empty": false, "max_stack": 3, "movable": true, "group": 1, "classroom_types": [1, 2, 3]}, {"subject_id": 1, "subject_name_id": 1, "class_id": 11, "number_of_groups": 2, "subject_length": 1, "lesson_hour_id": 2, "teachers_id": [5, 9], "classroom_id": 2, "is_empty": false, "max_stack": 3, "movable": true, "group": 2, "classroom_types": [1, 2, 3]}], [{"subject_id": 3, "subject_name_id": 3, "class_id": 11, "number_of_groups": 1, "subject_length": 1, "lesson_hour_id": 3, "teachers_id": [9], "classroom_id": 6, "is_empty": false, "max_stack": 3, "movable": true, "group": 0, "classroom_types": [1, 2, 3]}], [{"subject_id": 15, "subject_name_id": 15, "class_id": 11, "number_of_groups": 1, "subject_length": 1, "lesson_hour_id": 4, "teachers_id": [14], "classroom_id": 10, "is_empty": false, "max_stack": 3, "movable": true, "group": 0, "classroom_types": [1, 2, 3]}], [{"subject_id": 7, "subject_name_id": 7, "class_id": 11, "number_of_groups": 1, "subject_length": 1, "lesson_hour_id": 5, "teachers_id": [6], "classroom_id": 3, "is_empty": false, "max_stack": 2, "movable": true, "group": 0, "classroom_types": [1, 2, 3]}], [{"subject_id": 2, "subject_name_id": 2, "class_id": 11, "number_of_groups": 2, "subject_length": 1, "lesson_hour_id": 6, "teachers_id": [8], "classroom_id": 5, "is_empty": false, "max_stack": 3, "movable": true, "group": 1, "classroom_types": [1, 2, 3]}, {"subject_id": 11, "subject_name_id": 11, "class_id": 11, "number_of_groups": 2, "subject_length": 1, "lesson_hour_id": 6, "teachers_id": [23, 26], "classroom_id": 18, "is_empty": false, "max_stack": 2, "movable": true, "group": 2, "classroom_types": [1, 2, 3]}]], "wednesday": [[{"subject_id": 11, "subject_name_id": 11, "class_id": 11, "number_of_groups": 2, "subject_length": 1, "lesson_hour_id": 0, "teachers_id": [26], "classroom_id": 21, "is_empty": false, "max_stack": 2, "movable": true, "group": 1, "classroom_types": [1, 2, 3]}, {"subject_id": 11, "subject_name_id": 11, "class_id": 11, "number_of_groups": 2, "subject_length": 1, "lesson_hour_id": 0, "teachers_id": [23, 26], "classroom_id": 18, "is_empty": false, "max_stack": 2, "movable": true, "group": 2, "classroom_types": [1, 2, 3]}], [{"subject_id": 13, "subject_name_id": 13, "class_id": 11, "number_of_groups": 1, "subject_length": 1, "lesson_hour_id": 1, "teachers_id": [27], "classroom_id": 22, "is_empty": false, "max_stack": 2, "movable": true, "group": 0, "classroom_types": [1, 2, 3]}], [{"subject_id": 13, "subject_name_id": 13, "class_id": 11, "number_of_groups": 1, "subject_length": 1, "lesson_hour_id": 2, "teachers_id": [27], "classroom_id": 22, "is_empty": false, "max_stack": 2, "movable": true, "group": 0, "classroom_types": [1, 2, 3]}], [{"subject_id": 1, "subject_name_id": 1, "class_id": 11, "number_of_groups": 2, "subject_length": 1, "lesson_hour_id": 3, "teachers_id": [9], "classroom_id": 6, "is_empty": false, "max_stack": 3, "movable": true, "group": 1, "classroom_types": [1, 2, 3]}, {"subject_id": 1, "subject_name_id": 1, "class_id": 11, "number_of_groups": 2, "subject_length": 1, "lesson_hour_id": 3, "teachers_id": [5, 9], "classroom_id": 2, "is_empty": false, "max_stack": 3, "movable": true, "group": 2, "classroom_types": [1, 2, 3]}], [{"subject_id": 1, "subject_name_id": 1, "class_id": 11, "number_of_groups": 2, "subject_length": 1, "lesson_hour_id": 4, "teachers_id": [9], "classroom_id": 6, "is_empty": false, "max_stack": 3, "movable": true, "group": 1, "classroom_types": [1, 2, 3]}, {"subject_id": 1, "subject_name_id": 1, "class_id": 11, "number_of_groups": 2, "subject_length": 1, "lesson_hour_id": 4, "teachers_id": [5, 9], "classroom_id": 2, "is_empty": false, "max_stack": 3, "movable": true, "group": 2, "classroom_types": [1, 2, 3]}], [{"subject_id": 2, "subject_name_id": 2, "class_id": 11, "number_of_groups": 2, "subject_length": 1, "lesson_hour_id": 5, "teachers_id": [8], "classroom_id": 5, "is_empty": false, "max_stack": 3, "movable": true, "group": 1, "classroom_types": [1, 2, 3]}, {"subject_id": 12, "subject_name_id": 12, "class_id": 11, "number_of_groups": 2, "subject_length": 1, "lesson_hour_id": 5, "teachers_id": [24, 19], "classroom_id": 19, "is_empty": false, "max_stack": 2, "movable": true, "group": 2, "classroom_types": [1, 2, 3]}], [{"subject_id": 3, "subject_name_id": 3, "class_id": 11, "number_of_groups": 1, "subject_length": 1, "lesson_hour_id": 6, "teachers_id": [9], "classroom_id": 6, "is_empty": false, "max_stack": 3, "movable": true, "group": 0, "classroom_types": [1, 2, 3]}]], "thursday": [[{"subject_id": 1, "subject_name_id": 1, "class_id": 11, "number_of_groups": 2, "subject_length": 1, "lesson_hour_id": 0, "teachers_id": [9], "classroom_id": 6, "is_empty": false, "max_stack": 3, "movable": true, "group": 1, "classroom_types": [1, 2, 3]}, {"subject_id": 1, "subject_name_id": 1, "class_id": 11, "number_of_groups": 2, "subject_length": 1, "lesson_hour_id": 0, "teachers_id": [5, 9], "classroom_id": 2, "is_empty": false, "max_stack": 3, "movable": true, "group": 2, "classroom_types": [1, 2, 3]}], [{"subject_id": 13, "subject_name_id": 13, "class_id": 11, "number_of_groups": 1, "subject_length": 1, "lesson_hour_id": 1, "teachers_id": [27], "classroom_id": 22, "is_empty": false, "max_stack": 2, "movable": true, "group": 0, "classroom_types": [1, 2, 3]}], [{"subject_id": 4, "subject_name_id": 4, "class_id": 11, "number_of_groups": 1, "subject_length": 1, "lesson_hour_id": 2, "teachers_id": [15], "classroom_id": 11, "is_empty": false, "max_stack": 2, "movable": true, "group": 0, "classroom_types": [1, 2, 3]}], [{"subject_id": 7, "subject_name_id": 7, "class_id": 11, "number_of_groups": 1, "subject_length": 1, "lesson_hour_id": 3, "teachers_id": [6], "classroom_id": 3, "is_empty": false, "max_stack": 2, "movable": true, "group": 0, "classroom_types": [1, 2, 3]}], [{"subject_id": 12, "subject_name_id": 12, "class_id": 11, "number_of_groups": 2, "subject_length": 1, "lesson_hour_id": 4, "teachers_id": [19], "classroom_id": 15, "is_empty": false, "max_stack": 2, "movable": true, "group": 1, "classroom_types": [1, 2, 3]}, {"subject_id": 12, "subject_name_id": 12, "class_id": 11, "number_of_groups": 2, "subject_length": 1, "lesson_hour_id": 4, "teachers_id": [24, 19], "classroom_id": 19, "is_empty": false, "max_stack": 2, "movable": true, "group": 2, "classroom_types": [1, 2, 3]}], [{"subject_id": 16, "subject_name_id": 16, "class_id": 11, "number_of_groups": 1, "subject_length": 1, "lesson_hour_id": 5, "teachers_id": [19], "classroom_id": 15, "is_empty": false, "max_stack": 2, "movable": true, "group": 0, "classroom_types": [1, 2, 3]}], [{"subject_id": 17, "subject_name_id": 17, "class_id": 11, "number_of_groups": 1, "subject_length": 1, "lesson_hour_id": 6, "teachers_id": [20], "classroom_id": 16, "is_empty": false, "max_stack": 2, "movable": true, "group": 0, "classroom_types": [1, 2, 3]}], [{"subject_id": 11, "subject_name_id": 11, "class_id": 11, "number_of_groups": 2, "subject_length": 1, "lesson_hour_id": 7, "teachers_id": [26], "classroom_id": 21, "is_empty": false, "max_stack": 2, "movable": true, "group": 1, "classroom_types": [1, 2, 3]}, {"subject_id": 11, "subject_name_id": 11, "class_id": 11, "number_of_groups": 2, "subject_length": 1, "lesson_hour_id": 7, "teachers_id": [23, 26], "classroom_id": 18, "is_empty": false, "max_stack": 2, "movable": true, "group": 2, "classroom_types": [1, 2, 3]}], [{"subject_id": 8, "subject_name_id": 8, "class_id": 11, "number_of_groups": 1, "subject_length": 1, "lesson_hour_id": 8, "teachers_id": [51], "classroom_id": 35, "is_empty": false, "max_stack": 2, "movable": true, "group": 0, "classroom_types": [1, 2, 3]}], [{"subject_id": 11, "subject_name_id": 11, "class_id": 11, "number_of_groups": 2, "subject_length": 1, "lesson_hour_id": 9, "teachers_id": [26], "classroom_id": 21, "is_empty": false, "max_stack": 2, "movable": true, "group": 1, "classroom_types": [1, 2, 3]}, {"subject_id": 11, "subject_name_id": 11, "class_id": 11, "number_of_groups": 2, "subject_length": 1, "lesson_hour_id": 9, "teachers_id": [23, 26], "classroom_id": 18, "is_empty": false, "max_stack": 2, "movable": true, "group": 2, "classroom_types": [1, 2, 3]}]], "friday": [[{"subject_id": 11, "subject_name_id": 11, "class_id": 11, "number_of_groups": 2, "subject_length": 1, "lesson_hour_id": 0, "teachers_id": [26], "classroom_id": 21, "is_empty": false, "max_stack": 2, "movable": true, "group": 1, "classroom_types": [1, 2, 3]}, {"subject_id": 11, "subject_name_id": 11, "class_id": 11, "number_of_groups": 2, "subject_length": 1, "lesson_hour_id": 0, "teachers_id": [23, 26], "classroom_id": 18, "is_empty": false, "max_stack": 2, "movable": true, "group": 2, "classroom_types": [1, 2, 3]}], [{"subject_id": 11, "subject_name_id": 11, "class_id": 11, "number_of_groups": 2, "subject_length": 1, "lesson_hour_id": 1, "teachers_id": [26], "classroom_id": 21, "is_empty": false, "max_stack": 2, "movable": true, "group": 1, "classroom_types": [1, 2, 3]}, {"subject_id": 11, "subject_name_id": 11, "class_id": 11, "number_of_groups": 2, "subject_length": 1, "lesson_hour_id": 1, "teachers_id": [23, 26], "classroom_id": 18, "is_empty": false, "max_stack": 2, "movable": true, "group": 2, "classroom_types": [1, 2, 3]}], [{"subject_id": 1, "subject_name_id": 1, "class_id": 11, "number_of_groups": 2, "subject_length": 1, "lesson_hour_id": 2, "teachers_id": [9], "classroom_id": 6, "is_empty": false, "max_stack": 3, "movable": true, "group": 1, "classroom_types": [1, 2, 3]}, {"subject_id": 1, "subject_name_id": 1, "class_id": 11, "number_of_groups": 2, "subject_length": 1, "lesson_hour_id": 2, "teachers_id": [5, 9], "classroom_id": 2, "is_empty": false, "max_stack": 3, "movable": true, "group": 2, "classroom_types": [1, 2, 3]}], [{"subject_id": 4, "subject_name_id": 4, "class_id": 11, "number_of_groups": 1, "subject_length": 1, "lesson_hour_id": 3, "teachers_id": [15], "classroom_id": 11, "is_empty": false, "max_stack": 2, "movable": true, "group": 0, "classroom_types": [1, 2, 3]}], [{"subject_id": 14, "subject_name_id": 14, "class_id": 11, "number_of_groups": 1, "subject_length": 1, "lesson_hour_id": 4, "teachers_id": [18], "classroom_id": 14, "is_empty": false, "max_stack": 3, "movable": true, "group": 0, "classroom_types": [1, 2, 3]}], [{"subject_id": 16, "subject_name_id": 16, "class_id": 11, "number_of_groups": 1, "subject_length": 1, "lesson_hour_id": 5, "teachers_id": [19], "classroom_id": 15, "is_empty": false, "max_stack": 2, "movable": true, "group": 0, "classroom_types": [1, 2, 3]}], [{"subject_id": 11, "subject_name_id": 11, "class_id": 11, "number_of_groups": 2, "subject_length": 1, "lesson_hour_id": 6, "teachers_id": [26], "classroom_id": 21, "is_empty": false, "max_stack": 2, "movable": true, "group": 1, "classroom_types": [1, 2, 3]}, {"subject_id": 11, "subject_name_id": 11, "class_id": 11, "number_of_groups": 2, "subject_length": 1, "lesson_hour_id": 6, "teachers_id": [23, 26], "classroom_id": 18, "is_empty": false, "max_stack": 2, "movable": true, "group": 2, "classroom_types": [1, 2, 3]}]]}, "12": {"monday": [[{"subject_id": -1, "subject_name_id": null, "class_id": null, "number_of_groups": 0, "subject_length": 0, "lesson_hour_id": null, "teachers_id": [-1], "classroom_id": null, "is_empty": true, "max_stack": null, "movable": false, "group": 0, "classroom_types": []}], [{"subject_id": -1, "subject_name_id": null, "class_id": null, "number_of_groups": 0, "subject_length": 0, "lesson_hour_id": null, "teachers_id": [-1], "classroom_id": null, "is_empty": true, "max_stack": null, "movable": false, "group": 0, "classroom_types": []}], [{"subject_id": -1, "subject_name_id": null, "class_id": null, "number_of_groups": 0, "subject_length": 0, "lesson_hour_id": null, "teachers_id": [-1], "classroom_id": null, "is_empty": true, "max_stack": null, "movable": false, "group": 0, "classroom_types": []}], [{"subject_id": 22, "subject_name_id": 5, "class_id": 12, "number_of_groups": 1, "subject_length": 1, "lesson_hour_id": 3, "teachers_id": [12], "classroom_id": 2, "is_empty": false, "max_stack": 2, "movable": true, "group": 0, "classroom_types": [1, 2, 3]}], [{"subject_id": 34, "subject_name_id": 17, "class_id": 12, "number_of_groups": 1, "subject_length": 1, "lesson_hour_id": 4, "teachers_id": [29], "classroom_id": 1, "is_empty": false, "max_stack": 3, "movable": true, "group": 0, "classroom_types": [1, 2, 3]}], [{"subject_id": 23, "subject_name_id": 6, "class_id": 12, "number_of_groups": 1, "subject_length": 1, "lesson_hour_id": 5, "teachers_id": [13], "classroom_id": 9, "is_empty": false, "max_stack": 2, "movable": true, "group": 0, "classroom_types": [1, 2, 3]}], [{"subject_id": 28, "subject_name_id": 11, "class_id": 12, "number_of_groups": 2, "subject_length": 1, "lesson_hour_id": 6, "teachers_id": [13], "classroom_id": 9, "is_empty": false, "max_stack": 2, "movable": true, "group": 1, "classroom_types": [1, 2, 3]}, {"subject_id": 18, "subject_name_id": 1, "class_id": 12, "number_of_groups": 2, "subject_length": 1, "lesson_hour_id": 6, "teachers_id": [21], "classroom_id": 17, "is_empty": false, "max_stack": 2, "movable": true, "group": 2, "classroom_types": [1, 2, 3]}], [{"subject_id": 28, "subject_name_id": 11, "class_id": 12, "number_of_groups": 2, "subject_length": 1, "lesson_hour_id": 7, "teachers_id": [13], "classroom_id": 9, "is_empty": false, "max_stack": 2, "movable": true, "group": 1, "classroom_types": [1, 2, 3]}, {"subject_id": 18, "subject_name_id": 1, "class_id": 12, "number_of_groups": 2, "subject_length": 1, "lesson_hour_id": 7, "teachers_id": [21], "classroom_id": 17, "is_empty": false, "max_stack": 2, "movable": true, "group": 2, "classroom_types": [1, 2, 3]}], [{"subject_id": 19, "subject_name_id": 2, "class_id": 12, "number_of_groups": 2, "subject_length": 1, "lesson_hour_id": 8, "teachers_id": [11], "classroom_id": 8, "is_empty": false, "max_stack": 3, "movable": true, "group": 1, "classroom_types": [1, 2, 3]}, {"subject_id": 18, "subject_name_id": 1, "class_id": 12, "number_of_groups": 2, "subject_length": 1, "lesson_hour_id": 8, "teachers_id": [21], "classroom_id": 17, "is_empty": false, "max_stack": 2, "movable": true, "group": 2, "classroom_types": [1, 2, 3]}], [{"subject_id": 21, "subject_name_id": 4, "class_id": 12, "number_of_groups": 1, "subject_length": 1, "lesson_hour_id": 9, "teachers_id": [6], "classroom_id": 3, "is_empty": false, "max_stack": 3, "movable": true, "group": 0, "classroom_types": [1, 2, 3]}], [{"subject_id": 28, "subject_name_id": 11, "class_id": 12, "number_of_groups": 2, "subject_length": 1, "lesson_hour_id": 10, "teachers_id": [13], "classroom_id": 9, "is_empty": false, "max_stack": 2, "movable": true, "group": 1, "classroom_types": [1, 2, 3]}, {"subject_id": 28, "subject_name_id": 11, "class_id": 12, "number_of_groups": 2, "subject_length": 1, "lesson_hour_id": 10, "teachers_id": [10, 13], "classroom_id": 7, "is_empty": false, "max_stack": 2, "movable": true, "group": 2, "classroom_types": [1, 2, 3]}], [{"subject_id": 29, "subject_name_id": 12, "class_id": 12, "number_of_groups": 2, "subject_length": 1, "lesson_hour_id": 11, "teachers_id": [18], "classroom_id": 14, "is_empty": false, "max_stack": 4, "movable": true, "group": 1, "classroom_types": [1, 2, 3]}, {"subject_id": 29, "subject_name_id": 12, "class_id": 12, "number_of_groups": 2, "subject_length": 1, "lesson_hour_id": 11, "teachers_id": [14, 18], "classroom_id": 10, "is_empty": false, "max_stack": 4, "movable": true, "group": 2, "classroom_types": [1, 2, 3]}]], "tuesday": [[{"subject_id": -1, "subject_name_id": null, "class_id": null, "number_of_groups": 0, "subject_length": 0, "lesson_hour_id": null, "teachers_id": [-1], "classroom_id": null, "is_empty": true, "max_stack": null, "movable": false, "group": 0, "classroom_types": []}], [{"subject_id": -1, "subject_name_id": null, "class_id": null, "number_of_groups": 0, "subject_length": 0, "lesson_hour_id": null, "teachers_id": [-1], "classroom_id": null, "is_empty": true, "max_stack": null, "movable": false, "group": 0, "classroom_types": []}], [{"subject_id": -1, "subject_name_id": null, "class_id": null, "number_of_groups": 0, "subject_length": 0, "lesson_hour_id": null, "teachers_id": [-1], "classroom_id": null, "is_empty": true, "max_stack": null, "movable": false, "group": 0, "classroom_types": []}], [{"subject_id": 20, "subject_name_id": 3, "class_id": 12, "number_of_groups": 1, "subject_length": 1, "lesson_hour_id": 3, "teachers_id": [23], "classroom_id": 18, "is_empty": false, "max_stack": 3, "movable": true, "group": 0, "classroom_types": [1, 2, 3]}], [{"subject_id": 33, "subject_name_id": 16, "class_id": 12, "number_of_groups": 1, "subject_length": 1, "lesson_hour_id": 4, "teachers_id": [23], "classroom_id": 18, "is_empty": false, "max_stack": 2, "movable": true, "group": 0, "classroom_types": [1, 2, 3]}], [{"subject_id": 25, "subject_name_id": 8, "class_id": 12, "number_of_groups": 1, "subject_length": 1, "lesson_hour_id": 5, "teachers_id": [37], "classroom_id": 37, "is_empty": false, "max_stack": 2, "movable": true, "group": 0, "classroom_types": [1, 2, 3]}], [{"subject_id": 32, "subject_name_id": 15, "class_id": 12, "number_of_groups": 1, "subject_length": 1, "lesson_hour_id": 6, "teachers_id": [35], "classroom_id": 39, "is_empty": false, "max_stack": 3, "movable": true, "group": 0, "classroom_types": [1, 2, 3]}], [{"subject_id": 30, "subject_name_id": 13, "class_id": 12, "number_of_groups": 1, "subject_length": 1, "lesson_hour_id": 7, "teachers_id": [38], "classroom_id": 36, "is_empty": false, "max_stack": 4, "movable": true, "group": 0, "classroom_types": [1, 2, 3]}], [{"subject_id": 30, "subject_name_id": 13, "class_id": 12, "number_of_groups": 1, "subject_length": 1, "lesson_hour_id": 8, "teachers_id": [38], "classroom_id": 36, "is_empty": false, "max_stack": 4, "movable": true, "group": 0, "classroom_types": [1, 2, 3]}], [{"subject_id": 28, "subject_name_id": 11, "class_id": 12, "number_of_groups": 2, "subject_length": 1, "lesson_hour_id": 9, "teachers_id": [13], "classroom_id": 9, "is_empty": false, "max_stack": 2, "movable": true, "group": 1, "classroom_types": [1, 2, 3]}, {"subject_id": 28, "subject_name_id": 11, "class_id": 12, "number_of_groups": 2, "subject_length": 1, "lesson_hour_id": 9, "teachers_id": [10, 13], "classroom_id": 7, "is_empty": false, "max_stack": 2, "movable": true, "group": 2, "classroom_types": [1, 2, 3]}]], "wednesday": [[{"subject_id": -1, "subject_name_id": null, "class_id": null, "number_of_groups": 0, "subject_length": 0, "lesson_hour_id": null, "teachers_id": [-1], "classroom_id": null, "is_empty": true, "max_stack": null, "movable": false, "group": 0, "classroom_types": []}], [{"subject_id": -1, "subject_name_id": null, "class_id": null, "number_of_groups": 0, "subject_length": 0, "lesson_hour_id": null, "teachers_id": [-1], "classroom_id": null, "is_empty": true, "max_stack": null, "movable": false, "group": 0, "classroom_types": []}], [{"subject_id": -1, "subject_name_id": null, "class_id": null, "number_of_groups": 0, "subject_length": 0, "lesson_hour_id": null, "teachers_id": [-1], "classroom_id": null, "is_empty": true, "max_stack": null, "movable": false, "group": 0, "classroom_types": []}], [{"subject_id": 28, "subject_name_id": 11, "class_id": 12, "number_of_groups": 2, "subject_length": 1, "lesson_hour_id": 3, "teachers_id": [13], "classroom_id": 9, "is_empty": false, "max_stack": 2, "movable": true, "group": 1, "classroom_types": [1, 2, 3]}, {"subject_id": 28, "subject_name_id": 11, "class_id": 12, "number_of_groups": 2, "subject_length": 1, "lesson_hour_id": 3, "teachers_id": [10, 13], "classroom_id": 7, "is_empty": false, "max_stack": 2, "movable": true, "group": 2, "classroom_types": [1, 2, 3]}], [{"subject_id": 28, "subject_name_id": 11, "class_id": 12, "number_of_groups": 2, "subject_length": 1, "lesson_hour_id": 4, "teachers_id": [13], "classroom_id": 9, "is_empty": false, "max_stack": 2, "movable": true, "group": 1, "classroom_types": [1, 2, 3]}, {"subject_id": 28, "subject_name_id": 11, "class_id": 12, "number_of_groups": 2, "subject_length": 1, "lesson_hour_id": 4, "teachers_id": [10, 13], "classroom_id": 7, "is_empty": false, "max_stack": 2, "movable": true, "group": 2, "classroom_types": [1, 2, 3]}], [{"subject_id": 20, "subject_name_id": 3, "class_id": 12, "number_of_groups": 1, "subject_length": 1, "lesson_hour_id": 5, "teachers_id": [23], "classroom_id": 18, "is_empty": false, "max_stack": 3, "movable": true, "group": 0, "classroom_types": [1, 2, 3]}], [{"subject_id": 24, "subject_name_id": 7, "class_id": 12, "number_of_groups": 1, "subject_length": 1, "lesson_hour_id": 6, "teachers_id": [16], "classroom_id": 12, "is_empty": false, "max_stack": 2, "movable": true, "group": 0, "classroom_types": [1, 2, 3]}], [{"subject_id": 19, "subject_name_id": 2, "class_id": 12, "number_of_groups": 2, "subject_length": 1, "lesson_hour_id": 7, "teachers_id": [11], "classroom_id": 8, "is_empty": false, "max_stack": 3, "movable": true, "group": 1, "classroom_types": [1, 2, 3]}, {"subject_id": 19, "subject_name_id": 2, "class_id": 12, "number_of_groups": 2, "subject_length": 1, "lesson_hour_id": 7, "teachers_id": [2, 11], "classroom_id": 1, "is_empty": false, "max_stack": 3, "movable": true, "group": 2, "classroom_types": [1, 2, 3]}], [{"subject_id": 26, "subject_name_id": 9, "class_id": 12, "number_of_groups": 1, "subject_length": 1, "lesson_hour_id": 8, "teachers_id": [48], "classroom_id": 32, "is_empty": false, "max_stack": 2, "movable": true, "group": 0, "classroom_types": [1, 2, 3]}], [{"subject_id": 27, "subject_name_id": 10, "class_id": 12, "number_of_groups": 1, "subject_length": 1, "lesson_hour_id": 9, "teachers_id": [50], "classroom_id": 34, "is_empty": false, "max_stack": 2, "movable": true, "group": 0, "classroom_types": [1, 2, 3]}]], "thursday": [[{"subject_id": -1, "subject_name_id": null, "class_id": null, "number_of_groups": 0, "subject_length": 0, "lesson_hour_id": null, "teachers_id": [-1], "classroom_id": null, "is_empty": true, "max_stack": null, "movable": false, "group": 0, "classroom_types": []}], [{"subject_id": -1, "subject_name_id": null, "class_id": null, "number_of_groups": 0, "subject_length": 0, "lesson_hour_id": null, "teachers_id": [-1], "classroom_id": null, "is_empty": true, "max_stack": null, "movable": false, "group": 0, "classroom_types": []}], [{"subject_id": -1, "subject_name_id": null, "class_id": null, "number_of_groups": 0, "subject_length": 0, "lesson_hour_id": null, "teachers_id": [-1], "classroom_id": null, "is_empty": true, "max_stack": null, "movable": false, "group": 0, "classroom_types": []}], [{"subject_id": 28, "subject_name_id": 11, "class_id": 12, "number_of_groups": 2, "subject_length": 1, "lesson_hour_id": 3, "teachers_id": [13], "classroom_id": 9, "is_empty": false, "max_stack": 2, "movable": true, "group": 1, "classroom_types": [1, 2, 3]}, {"subject_id": 28, "subject_name_id": 11, "class_id": 12, "number_of_groups": 2, "subject_length": 1, "lesson_hour_id": 3, "teachers_id": [10, 13], "classroom_id": 7, "is_empty": false, "max_stack": 2, "movable": true, "group": 2, "classroom_types": [1, 2, 3]}], [{"subject_id": 28, "subject_name_id": 11, "class_id": 12, "number_of_groups": 2, "subject_length": 1, "lesson_hour_id": 4, "teachers_id": [13], "classroom_id": 9, "is_empty": false, "max_stack": 2, "movable": true, "group": 1, "classroom_types": [1, 2, 3]}, {"subject_id": 28, "subject_name_id": 11, "class_id": 12, "number_of_groups": 2, "subject_length": 1, "lesson_hour_id": 4, "teachers_id": [10, 13], "classroom_id": 7, "is_empty": false, "max_stack": 2, "movable": true, "group": 2, "classroom_types": [1, 2, 3]}], [{"subject_id": 33, "subject_name_id": 16, "class_id": 12, "number_of_groups": 1, "subject_length": 1, "lesson_hour_id": 5, "teachers_id": [23], "classroom_id": 18, "is_empty": false, "max_stack": 2, "movable": true, "group": 0, "classroom_types": [1, 2, 3]}], [{"subject_id": 30, "subject_name_id": 13, "class_id": 12, "number_of_groups": 1, "subject_length": 1, "lesson_hour_id": 6, "teachers_id": [38], "classroom_id": 36, "is_empty": false, "max_stack": 4, "movable": true, "group": 0, "classroom_types": [1, 2, 3]}], [{"subject_id": 19, "subject_name_id": 2, "class_id": 12, "number_of_groups": 2, "subject_length": 1, "lesson_hour_id": 7, "teachers_id": [11], "classroom_id": 8, "is_empty": false, "max_stack": 3, "movable": true, "group": 1, "classroom_types": [1, 2, 3]}, {"subject_id": 19, "subject_name_id": 2, "class_id": 12, "number_of_groups": 2, "subject_length": 1, "lesson_hour_id": 7, "teachers_id": [2, 11], "classroom_id": 1, "is_empty": false, "max_stack": 3, "movable": true, "group": 2, "classroom_types": [1, 2, 3]}], [{"subject_id": 20, "subject_name_id": 3, "class_id": 12, "number_of_groups": 1, "subject_length": 1, "lesson_hour_id": 8, "teachers_id": [23], "classroom_id": 18, "is_empty": false, "max_stack": 3, "movable": true, "group": 0, "classroom_types": [1, 2, 3]}], [{"subject_id": 18, "subject_name_id": 1, "class_id": 12, "number_of_groups": 2, "subject_length": 1, "lesson_hour_id": 9, "teachers_id": [21], "classroom_id": 17, "is_empty": false, "max_stack": 2, "movable": true, "group": 1, "classroom_types": [1, 2, 3]}, {"subject_id": 28, "subject_name_id": 11, "class_id": 12, "number_of_groups": 2, "subject_length": 1, "lesson_hour_id": 9, "teachers_id": [10, 13], "classroom_id": 7, "is_empty": false, "max_stack": 2, "movable": true, "group": 2, "classroom_types": [1, 2, 3]}]], "friday": [[{"subject_id": -1, "subject_name_id": null, "class_id": null, "number_of_groups": 0, "subject_length": 0, "lesson_hour_id": null, "teachers_id": [-1], "classroom_id": null, "is_empty": true, "max_stack": null, "movable": false, "group": 0, "classroom_types": []}], [{"subject_id": -1, "subject_name_id": null, "class_id": null, "number_of_groups": 0, "subject_length": 0, "lesson_hour_id": null, "teachers_id": [-1], "classroom_id": null, "is_empty": true, "max_stack": null, "movable": false, "group": 0, "classroom_types": []}], [{"subject_id": -1, "subject_name_id": null, "class_id": null, "number_of_groups": 0, "subject_length": 0, "lesson_hour_id": null, "teachers_id": [-1], "classroom_id": null, "is_empty": true, "max_stack": null, "movable": false, "group": 0, "classroom_types": []}], [{"subject_id": 28, "subject_name_id": 11, "class_id": 12, "number_of_groups": 2, "subject_length": 1, "lesson_hour_id": 3, "teachers_id": [13], "classroom_id": 9, "is_empty": false, "max_stack": 2, "movable": true, "group": 1, "classroom_types": [1, 2, 3]}, {"subject_id": 28, "subject_name_id": 11, "class_id": 12, "number_of_groups": 2, "subject_length": 1, "lesson_hour_id": 3, "teachers_id": [10, 13], "classroom_id": 7, "is_empty": false, "max_stack": 2, "movable": true, "group": 2, "classroom_types": [1, 2, 3]}], [{"subject_id": 28, "subject_name_id": 11, "class_id": 12, "number_of_groups": 2, "subject_length": 1, "lesson_hour_id": 4, "teachers_id": [13], "classroom_id": 9, "is_empty": false, "max_stack": 2, "movable": true, "group": 1, "classroom_types": [1, 2, 3]}, {"subject_id": 28, "subject_name_id": 11, "class_id": 12, "number_of_groups": 2, "subject_length": 1, "lesson_hour_id": 4, "teachers_id": [10, 13], "classroom_id": 7, "is_empty": false, "max_stack": 2, "movable": true, "group": 2, "classroom_types": [1, 2, 3]}], [{"subject_id": 20, "subject_name_id": 3, "class_id": 12, "number_of_groups": 1, "subject_length": 1, "lesson_hour_id": 5, "teachers_id": [23], "classroom_id": 18, "is_empty": false, "max_stack": 3, "movable": true, "group": 0, "classroom_types": [1, 2, 3]}], [{"subject_id": 21, "subject_name_id": 4, "class_id": 12, "number_of_groups": 1, "subject_length": 1, "lesson_hour_id": 6, "teachers_id": [6], "classroom_id": 3, "is_empty": false, "max_stack": 3, "movable": true, "group": 0, "classroom_types": [1, 2, 3]}], [{"subject_id": 31, "subject_name_id": 14, "class_id": 12, "number_of_groups": 1, "subject_length": 1, "lesson_hour_id": 7, "teachers_id": [7], "classroom_id": 4, "is_empty": false, "max_stack": 3, "movable": true, "group": 0, "classroom_types": [1, 2, 3]}], [{"subject_id": 19, "subject_name_id": 2, "class_id": 12, "number_of_groups": 2, "subject_length": 1, "lesson_hour_id": 8, "teachers_id": [11], "classroom_id": 8, "is_empty": false, "max_stack": 3, "movable": true, "group": 1, "classroom_types": [1, 2, 3]}, {"subject_id": 19, "subject_name_id": 2, "class_id": 12, "number_of_groups": 2, "subject_length": 1, "lesson_hour_id": 8, "teachers_id": [2, 11], "classroom_id": 1, "is_empty": false, "max_stack": 3, "movable": true, "group": 2, "classroom_types": [1, 2, 3]}], [{"subject_id": 29, "subject_name_id": 12, "class_id": 12, "number_of_groups": 2, "subject_length": 1, "lesson_hour_id": 9, "teachers_id": [18], "classroom_id": 14, "is_empty": false, "max_stack": 4, "movable": true, "group": 1, "classroom_types": [1, 2, 3]}, {"subject_id": 29, "subject_name_id": 12, "class_id": 12, "number_of_groups": 2, "subject_length": 1, "lesson_hour_id": 9, "teachers_id": [14, 18], "classroom_id": 10, "is_empty": false, "max_stack": 4, "movable": true, "group": 2, "classroom_types": [1, 2, 3]}], [{"subject_id": 18, "subject_name_id": 1, "class_id": 12, "number_of_groups": 2, "subject_length": 1, "lesson_hour_id": 10, "teachers_id": [21], "classroom_id": 17, "is_empty": false, "max_stack": 2, "movable": true, "group": 1, "classroom_types": [1, 2, 3]}, {"subject_id": 28, "subject_name_id": 11, "class_id": 12, "number_of_groups": 2, "subject_length": 1, "lesson_hour_id": 10, "teachers_id": [10, 13], "classroom_id": 7, "is_empty": false, "max_stack": 2, "movable": true, "group": 2, "classroom_types": [1, 2, 3]}], [{"subject_id": 18, "subject_name_id": 1, "class_id": 12, "number_of_groups": 2, "subject_length": 1, "lesson_hour_id": 11, "teachers_id": [21], "classroom_id": 17, "is_empty": false, "max_stack": 2, "movable": true, "group": 1, "classroom_types": [1, 2, 3]}, {"subject_id": 19, "subject_name_id": 2, "class_id": 12, "number_of_groups": 2, "subject_length": 1, "lesson_hour_id": 11, "teachers_id": [2, 11], "classroom_id": 1, "is_empty": false, "max_stack": 3, "movable": true, "group": 2, "classroom_types": [1, 2, 3]}]]}, "13": {"monday": [[{"subject_id": 49, "subject_name_id": 15, "class_id": 13, "number_of_groups": 1, "subject_length": 1, "lesson_hour_id": 0, "teachers_id": [1], "classroom_id": 1, "is_empty": false, "max_stack": 2, "movable": true, "group": 0, "classroom_types": [1, 2, 3]}], [{"subject_id": 35, "subject_name_id": 1, "class_id": 13, "number_of_groups": 2, "subject_length": 1, "lesson_hour_id": 1, "teachers_id": [33], "classroom_id": 1, "is_empty": false, "max_stack": 3, "movable": true, "group": 1, "classroom_types": [1, 2, 3]}, {"subject_id": 35, "subject_name_id": 1, "class_id": 13, "number_of_groups": 2, "subject_length": 1, "lesson_hour_id": 1, "teachers_id": [31, 33], "classroom_id": 2, "is_empty": false, "max_stack": 3, "movable": true, "group": 2, "classroom_types": [1, 2, 3]}], [{"subject_id": 35, "subject_name_id": 1, "class_id": 13, "number_of_groups": 2, "subject_length": 1, "lesson_hour_id": 2, "teachers_id": [33], "classroom_id": 1, "is_empty": false, "max_stack": 3, "movable": true, "group": 1, "classroom_types": [1, 2, 3]}, {"subject_id": 35, "subject_name_id": 1, "class_id": 13, "number_of_groups": 2, "subject_length": 1, "lesson_hour_id": 2, "teachers_id": [31, 33], "classroom_id": 2, "is_empty": false, "max_stack": 3, "movable": true, "group": 2, "classroom_types": [1, 2, 3]}], [{"subject_id": 46, "subject_name_id": 12, "class_id": 13, "number_of_groups": 2, "subject_length": 1, "lesson_hour_id": 3, "teachers_id": [33], "classroom_id": 3, "is_empty": false, "max_stack": 2, "movable": true, "group": 1, "classroom_types": [1, 2, 3]}, {"subject_id": 46, "subject_name_id": 12, "class_id": 13, "number_of_groups": 2, "subject_length": 1, "lesson_hour_id": 3, "teachers_id": [30, 33], "classroom_id": 4, "is_empty": false, "max_stack": 2, "movable": true, "group": 2, "classroom_types": [1, 2, 3]}], [{"subject_id": 48, "subject_name_id": 14, "class_id": 13, "number_of_groups": 1, "subject_length": 1, "lesson_hour_id": 4, "teachers_id": [34], "classroom_id": 2, "is_empty": false, "max_stack": 2, "movable": true, "group": 0, "classroom_types": [1, 2, 3]}], [{"subject_id": 36, "subject_name_id": 2, "class_id": 13, "number_of_groups": 2, "subject_length": 1, "lesson_hour_id": 5, "teachers_id": [41], "classroom_id": 25, "is_empty": false, "max_stack": 3, "movable": true, "group": 1, "classroom_types": [1, 2, 3]}, {"subject_id": 36, "subject_name_id": 2, "class_id": 13, "number_of_groups": 2, "subject_length": 1, "lesson_hour_id": 5, "teachers_id": [45, 41], "classroom_id": 29, "is_empty": false, "max_stack": 3, "movable": true, "group": 2, "classroom_types": [1, 2, 3]}], [{"subject_id": 51, "subject_name_id": 17, "class_id": 13, "number_of_groups": 1, "subject_length": 1, "lesson_hour_id": 6, "teachers_id": [42], "classroom_id": 26, "is_empty": false, "max_stack": 3, "movable": true, "group": 0, "classroom_types": [1, 2, 3]}], [{"subject_id": 47, "subject_name_id": 13, "class_id": 13, "number_of_groups": 1, "subject_length": 1, "lesson_hour_id": 7, "teachers_id": [22], "classroom_id": 1, "is_empty": false, "max_stack": 2, "movable": true, "group": 0, "classroom_types": [1, 2, 3]}], [{"subject_id": 47, "subject_name_id": 13, "class_id": 13, "number_of_groups": 1, "subject_length": 1, "lesson_hour_id": 8, "teachers_id": [22], "classroom_id": 1, "is_empty": false, "max_stack": 2, "movable": true, "group": 0, "classroom_types": [1, 2, 3]}]], "tuesday": [[{"subject_id": 38, "subject_name_id": 4, "class_id": 13, "number_of_groups": 1, "subject_length": 1, "lesson_hour_id": 0, "teachers_id": [3], "classroom_id": 1, "is_empty": false, "max_stack": 3, "movable": true, "group": 0, "classroom_types": [1, 2, 3]}], [{"subject_id": 45, "subject_name_id": 11, "class_id": 13, "number_of_groups": 2, "subject_length": 1, "lesson_hour_id": 1, "teachers_id": [32], "classroom_id": 1, "is_empty": false, "max_stack": 2, "movable": true, "group": 1, "classroom_types": [1, 2, 3]}, {"subject_id": 45, "subject_name_id": 11, "class_id": 13, "number_of_groups": 2, "subject_length": 1, "lesson_hour_id": 1, "teachers_id": [27, 32], "classroom_id": 22, "is_empty": false, "max_stack": 2, "movable": true, "group": 2, "classroom_types": [1, 2, 3]}], [{"subject_id": 45, "subject_name_id": 11, "class_id": 13, "number_of_groups": 2, "subject_length": 1, "lesson_hour_id": 2, "teachers_id": [32], "classroom_id": 1, "is_empty": false, "max_stack": 2, "movable": true, "group": 1, "classroom_types": [1, 2, 3]}, {"subject_id": 45, "subject_name_id": 11, "class_id": 13, "number_of_groups": 2, "subject_length": 1, "lesson_hour_id": 2, "teachers_id": [27, 32], "classroom_id": 22, "is_empty": false, "max_stack": 2, "movable": true, "group": 2, "classroom_types": [1, 2, 3]}], [{"subject_id": 45, "subject_name_id": 11, "class_id": 13, "number_of_groups": 2, "subject_length": 1, "lesson_hour_id": 3, "teachers_id": [32], "classroom_id": 1, "is_empty": false, "max_stack": 2, "movable": true, "group": 1, "classroom_types": [1, 2, 3]}, {"subject_id": 45, "subject_name_id": 11, "class_id": 13, "number_of_groups": 2, "subject_length": 1, "lesson_hour_id": 3, "teachers_id": [27, 32], "classroom_id": 22, "is_empty": false, "max_stack": 2, "movable": true, "group": 2, "classroom_types": [1, 2, 3]}], [{"subject_id": 35, "subject_name_id": 1, "class_id": 13, "number_of_groups": 2, "subject_length": 1, "lesson_hour_id": 4, "teachers_id": [33], "classroom_id": 1, "is_empty": false, "max_stack": 3, "movable": true, "group": 1, "classroom_types": [1, 2, 3]}, {"subject_id": 35, "subject_name_id": 1, "class_id": 13, "number_of_groups": 2, "subject_length": 1, "lesson_hour_id": 4, "teachers_id": [31, 33], "classroom_id": 2, "is_empty": false, "max_stack": 3, "movable": true, "group": 2, "classroom_types": [1, 2, 3]}], [{"subject_id": 35, "subject_name_id": 1, "class_id": 13, "number_of_groups": 2, "subject_length": 1, "lesson_hour_id": 5, "teachers_id": [33], "classroom_id": 1, "is_empty": false, "max_stack": 3, "movable": true, "group": 1, "classroom_types": [1, 2, 3]}, {"subject_id": 35, "subject_name_id": 1, "class_id": 13, "number_of_groups": 2, "subject_length": 1, "lesson_hour_id": 5, "teachers_id": [31, 33], "classroom_id": 2, "is_empty": false, "max_stack": 3, "movable": true, "group": 2, "classroom_types": [1, 2, 3]}], [{"subject_id": 36, "subject_name_id": 2, "class_id": 13, "number_of_groups": 2, "subject_length": 1, "lesson_hour_id": 6, "teachers_id": [41], "classroom_id": 25, "is_empty": false, "max_stack": 3, "movable": true, "group": 1, "classroom_types": [1, 2, 3]}, {"subject_id": 36, "subject_name_id": 2, "class_id": 13, "number_of_groups": 2, "subject_length": 1, "lesson_hour_id": 6, "teachers_id": [45, 41], "classroom_id": 29, "is_empty": false, "max_stack": 3, "movable": true, "group": 2, "classroom_types": [1, 2, 3]}], [{"subject_id": 47, "subject_name_id": 13, "class_id": 13, "number_of_groups": 1, "subject_length": 1, "lesson_hour_id": 7, "teachers_id": [22], "classroom_id": 1, "is_empty": false, "max_stack": 2, "movable": true, "group": 0, "classroom_types": [1, 2, 3]}], [{"subject_id": 39, "subject_name_id": 5, "class_id": 13, "number_of_groups": 1, "subject_length": 1, "lesson_hour_id": 8, "teachers_id": [49], "classroom_id": 33, "is_empty": false, "max_stack": 2, "movable": true, "group": 0, "classroom_types": [1, 2, 3]}], [{"subject_id": 38, "subject_name_id": 4, "class_id": 13, "number_of_groups": 1, "subject_length": 1, "lesson_hour_id": 9, "teachers_id": [3], "classroom_id": 1, "is_empty": false, "max_stack": 3, "movable": true, "group": 0, "classroom_types": [1, 2, 3]}]], "wednesday": [[{"subject_id": 38, "subject_name_id": 4, "class_id": 13, "number_of_groups": 1, "subject_length": 1, "lesson_hour_id": 0, "teachers_id": [3], "classroom_id": 1, "is_empty": false, "max_stack": 3, "movable": true, "group": 0, "classroom_types": [1, 2, 3]}], [{"subject_id": 44, "subject_name_id": 10, "class_id": 13, "number_of_groups": 1, "subject_length": 1, "lesson_hour_id": 1, "teachers_id": [29], "classroom_id": 1, "is_empty": false, "max_stack": 2, "movable": true, "group": 0, "classroom_types": [1, 2, 3]}], [{"subject_id": 35, "subject_name_id": 1, "class_id": 13, "number_of_groups": 2, "subject_length": 1, "lesson_hour_id": 2, "teachers_id": [33], "classroom_id": 1, "is_empty": false, "max_stack": 3, "movable": true, "group": 1, "classroom_types": [1, 2, 3]}, {"subject_id": 35, "subject_name_id": 1, "class_id": 13, "number_of_groups": 2, "subject_length": 1, "lesson_hour_id": 2, "teachers_id": [31, 33], "classroom_id": 2, "is_empty": false, "max_stack": 3, "movable": true, "group": 2, "classroom_types": [1, 2, 3]}], [{"subject_id": 35, "subject_name_id": 1, "class_id": 13, "number_of_groups": 2, "subject_length": 1, "lesson_hour_id": 3, "teachers_id": [33], "classroom_id": 1, "is_empty": false, "max_stack": 3, "movable": true, "group": 1, "classroom_types": [1, 2, 3]}, {"subject_id": 35, "subject_name_id": 1, "class_id": 13, "number_of_groups": 2, "subject_length": 1, "lesson_hour_id": 3, "teachers_id": [31, 33], "classroom_id": 3, "is_empty": false, "max_stack": 3, "movable": true, "group": 2, "classroom_types": [1, 2, 3]}], [{"subject_id": 50, "subject_name_id": 16, "class_id": 13, "number_of_groups": 1, "subject_length": 1, "lesson_hour_id": 4, "teachers_id": [44], "classroom_id": 28, "is_empty": false, "max_stack": 2, "movable": true, "group": 0, "classroom_types": [1, 2, 3]}], [{"subject_id": 36, "subject_name_id": 2, "class_id": 13, "number_of_groups": 2, "subject_length": 1, "lesson_hour_id": 5, "teachers_id": [41], "classroom_id": 25, "is_empty": false, "max_stack": 3, "movable": true, "group": 1, "classroom_types": [1, 2, 3]}, {"subject_id": 36, "subject_name_id": 2, "class_id": 13, "number_of_groups": 2, "subject_length": 1, "lesson_hour_id": 5, "teachers_id": [45, 41], "classroom_id": 29, "is_empty": false, "max_stack": 3, "movable": true, "group": 2, "classroom_types": [1, 2, 3]}], [{"subject_id": 46, "subject_name_id": 12, "class_id": 13, "number_of_groups": 2, "subject_length": 1, "lesson_hour_id": 6, "teachers_id": [33], "classroom_id": 1, "is_empty": false, "max_stack": 2, "movable": true, "group": 1, "classroom_types": [1, 2, 3]}, {"subject_id": 46, "subject_name_id": 12, "class_id": 13, "number_of_groups": 2, "subject_length": 1, "lesson_hour_id": 6, "teachers_id": [30, 33], "classroom_id": 2, "is_empty": false, "max_stack": 2, "movable": true, "group": 2, "classroom_types": [1, 2, 3]}], [{"subject_id": 45, "subject_name_id": 11, "class_id": 13, "number_of_groups": 2, "subject_length": 1, "lesson_hour_id": 7, "teachers_id": [32], "classroom_id": 2, "is_empty": false, "max_stack": 2, "movable": true, "group": 1, "classroom_types": [1, 2, 3]}, {"subject_id": 45, "subject_name_id": 11, "class_id": 13, "number_of_groups": 2, "subject_length": 1, "lesson_hour_id": 7, "teachers_id": [27, 32], "classroom_id": 22, "is_empty": false, "max_stack": 2, "movable": true, "group": 2, "classroom_types": [1, 2, 3]}], [{"subject_id": 45, "subject_name_id": 11, "class_id": 13, "number_of_groups": 2, "subject_length": 1, "lesson_hour_id": 8, "teachers_id": [32], "classroom_id": 2, "is_empty": false, "max_stack": 2, "movable": true, "group": 1, "classroom_types": [1, 2, 3]}, {"subject_id": 45, "subject_name_id": 11, "class_id": 13, "number_of_groups": 2, "subject_length": 1, "lesson_hour_id": 8, "teachers_id": [27, 32], "classroom_id": 22, "is_empty": false, "max_stack": 2, "movable": true, "group": 2, "classroom_types": [1, 2, 3]}], [{"subject_id": 45, "subject_name_id": 11, "class_id": 13, "number_of_groups": 2, "subject_length": 1, "lesson_hour_id": 9, "teachers_id": [32], "classroom_id": 1, "is_empty": false, "max_stack": 2, "movable": true, "group": 1, "classroom_types": [1, 2, 3]}, {"subject_id": 45, "subject_name_id": 11, "class_id": 13, "number_of_groups": 2, "subject_length": 1, "lesson_hour_id": 9, "teachers_id": [27, 32], "classroom_id": 22, "is_empty": false, "max_stack": 2, "movable": true, "group": 2, "classroom_types": [1, 2, 3]}]], "thursday": [[{"subject_id": 45, "subject_name_id": 11, "class_id": 13, "number_of_groups": 2, "subject_length": 1, "lesson_hour_id": 0, "teachers_id": [32], "classroom_id": 1, "is_empty": false, "max_stack": 2, "movable": true, "group": 1, "classroom_types": [1, 2, 3]}, {"subject_id": 45, "subject_name_id": 11, "class_id": 13, "number_of_groups": 2, "subject_length": 1, "lesson_hour_id": 0, "teachers_id": [27, 32], "classroom_id": 22, "is_empty": false, "max_stack": 2, "movable": true, "group": 2, "classroom_types": [1, 2, 3]}], [{"subject_id": 50, "subject_name_id": 16, "class_id": 13, "number_of_groups": 1, "subject_length": 1, "lesson_hour_id": 1, "teachers_id": [44], "classroom_id": 28, "is_empty": false, "max_stack": 2, "movable": true, "group": 0, "classroom_types": [1, 2, 3]}], [{"subject_id": 36, "subject_name_id": 2, "class_id": 13, "number_of_groups": 2, "subject_length": 1, "lesson_hour_id": 2, "teachers_id": [41], "classroom_id": 25, "is_empty": false, "max_stack": 3, "movable": true, "group": 1, "classroom_types": [1, 2, 3]}, {"subject_id": 36, "subject_name_id": 2, "class_id": 13, "number_of_groups": 2, "subject_length": 1, "lesson_hour_id": 2, "teachers_id": [45, 41], "classroom_id": 29, "is_empty": false, "max_stack": 3, "movable": true, "group": 2, "classroom_types": [1, 2, 3]}], [{"subject_id": 43, "subject_name_id": 9, "class_id": 13, "number_of_groups": 1, "subject_length": 1, "lesson_hour_id": 3, "teachers_id": [28], "classroom_id": 1, "is_empty": false, "max_stack": 3, "movable": true, "group": 0, "classroom_types": [1, 2, 3]}], [{"subject_id": 47, "subject_name_id": 13, "class_id": 13, "number_of_groups": 1, "subject_length": 1, "lesson_hour_id": 4, "teachers_id": [22], "classroom_id": 1, "is_empty": false, "max_stack": 2, "movable": true, "group": 0, "classroom_types": [1, 2, 3]}], [{"subject_id": 47, "subject_name_id": 13, "class_id": 13, "number_of_groups": 1, "subject_length": 1, "lesson_hour_id": 5, "teachers_id": [22], "classroom_id": 1, "is_empty": false, "max_stack": 2, "movable": true, "group": 0, "classroom_types": [1, 2, 3]}], [{"subject_id": 42, "subject_name_id": 8, "class_id": 13, "number_of_groups": 1, "subject_length": 1, "lesson_hour_id": 6, "teachers_id": [24], "classroom_id": 19, "is_empty": false, "max_stack": 2, "movable": true, "group": 0, "classroom_types": [1, 2, 3]}], [{"subject_id": 41, "subject_name_id": 7, "class_id": 13, "number_of_groups": 1, "subject_length": 1, "lesson_hour_id": 7, "teachers_id": [39], "classroom_id": 23, "is_empty": false, "max_stack": 4, "movable": true, "group": 0, "classroom_types": [1, 2, 3]}], [{"subject_id": 45, "subject_name_id": 11, "class_id": 13, "number_of_groups": 2, "subject_length": 1, "lesson_hour_id": 8, "teachers_id": [32], "classroom_id": 1, "is_empty": false, "max_stack": 2, "movable": true, "group": 1, "classroom_types": [1, 2, 3]}, {"subject_id": 45, "subject_name_id": 11, "class_id": 13, "number_of_groups": 2, "subject_length": 1, "lesson_hour_id": 8, "teachers_id": [27, 32], "classroom_id": 22, "is_empty": false, "max_stack": 2, "movable": true, "group": 2, "classroom_types": [1, 2, 3]}], [{"subject_id": 37, "subject_name_id": 3, "class_id": 13, "number_of_groups": 1, "subject_length": 1, "lesson_hour_id": 9, "teachers_id": [19], "classroom_id": 15, "is_empty": false, "max_stack": 2, "movable": true, "group": 0, "classroom_types": [1, 2, 3]}]], "friday": [[{"subject_id": 45, "subject_name_id": 11, "class_id": 13, "number_of_groups": 2, "subject_length": 1, "lesson_hour_id": 0, "teachers_id": [32], "classroom_id": 1, "is_empty": false, "max_stack": 2, "movable": true, "group": 1, "classroom_types": [1, 2, 3]}, {"subject_id": 45, "subject_name_id": 11, "class_id": 13, "number_of_groups": 2, "subject_length": 1, "lesson_hour_id": 0, "teachers_id": [27, 32], "classroom_id": 22, "is_empty": false, "max_stack": 2, "movable": true, "group": 2, "classroom_types": [1, 2, 3]}], [{"subject_id": 38, "subject_name_id": 4, "class_id": 13, "number_of_groups": 1, "subject_length": 1, "lesson_hour_id": 1, "teachers_id": [3], "classroom_id": 1, "is_empty": false, "max_stack": 3, "movable": true, "group": 0, "classroom_types": [1, 2, 3]}], [{"subject_id": 37, "subject_name_id": 3, "class_id": 13, "number_of_groups": 1, "subject_length": 1, "lesson_hour_id": 2, "teachers_id": [19], "classroom_id": 15, "is_empty": false, "max_stack": 2, "movable": true, "group": 0, "classroom_types": [1, 2, 3]}], [{"subject_id": 47, "subject_name_id": 13, "class_id": 13, "number_of_groups": 1, "subject_length": 1, "lesson_hour_id": 3, "teachers_id": [22], "classroom_id": 1, "is_empty": false, "max_stack": 2, "movable": true, "group": 0, "classroom_types": [1, 2, 3]}], [{"subject_id": 40, "subject_name_id": 6, "class_id": 13, "number_of_groups": 1, "subject_length": 1, "lesson_hour_id": 4, "teachers_id": [51], "classroom_id": 35, "is_empty": false, "max_stack": 3, "movable": true, "group": 0, "classroom_types": [1, 2, 3]}], [{"subject_id": 45, "subject_name_id": 11, "class_id": 13, "number_of_groups": 2, "subject_length": 1, "lesson_hour_id": 5, "teachers_id": [32], "classroom_id": 1, "is_empty": false, "max_stack": 2, "movable": true, "group": 1, "classroom_types": [1, 2, 3]}, {"subject_id": 45, "subject_name_id": 11, "class_id": 13, "number_of_groups": 2, "subject_length": 1, "lesson_hour_id": 5, "teachers_id": [27, 32], "classroom_id": 22, "is_empty": false, "max_stack": 2, "movable": true, "group": 2, "classroom_types": [1, 2, 3]}], [{"subject_id": 41, "subject_name_id": 7, "class_id": 13, "number_of_groups": 1, "subject_length": 1, "lesson_hour_id": 6, "teachers_id": [39], "classroom_id": 23, "is_empty": false, "max_stack": 4, "movable": true, "group": 0, "classroom_types": [1, 2, 3]}]]}}